clax/__init__.py
clax/_version.py
clax/clax.py
clax/network.py
clax-0.0.6.dist-info/LICENSE
clax-0.0.6.dist-info/METADATA
clax-0.0.6.dist-info/WHEEL
clax-0.0.6.dist-info/top_level.txt
clax-0.0.6.dist-info/RECORD
