Metadata-Version: 2.1
Name: clax
Version: 0.0.6
Summary: Prebuilt jax classifiers
Author-email: David Yallup <david.yallup@gmail.com>
License: MIT License
Requires-Python: >=3.9
License-File: LICENSE
Requires-Dist: flax >=0.8.2
Requires-Dist: tqdm >=4.62.0
Requires-Dist: optax >=0.2.2
Provides-Extra: metal
Requires-Dist: jax-metal ; extra == 'metal'
Provides-Extra: test
Requires-Dist: pytest ; extra == 'test'
Requires-Dist: pytest-cov ; extra == 'test'
Requires-Dist: flake8 ; extra == 'test'
Requires-Dist: pydocstyle ; extra == 'test'
Requires-Dist: packaging ; extra == 'test'
Requires-Dist: pre-commit ; extra == 'test'
